pycounts_jw19/__init__.py
pycounts_jw19/plotting.py
pycounts_jw19/pycounts_jw.py
pycounts_jw19/zen.txt
pycounts_jw19-0.1.1.dist-info/LICENSE
pycounts_jw19-0.1.1.dist-info/METADATA
pycounts_jw19-0.1.1.dist-info/WHEEL
pycounts_jw19-0.1.1.dist-info/RECORD
